<?xml version="1.0" encoding="UTF-8"?>
<GraphicalSchema xmlns="http://v8.1c.ru/8.3/xcf/scheme" xmlns:sch="http://v8.1c.ru/8.2/data/graphscheme" xmlns:style="http://v8.1c.ru/8.1/data/ui/style" xmlns:v8="http://v8.1c.ru/8.1/data/core" xmlns:v8ui="http://v8.1c.ru/8.1/data/ui" xmlns:web="http://v8.1c.ru/8.1/data/ui/colors/web" xmlns:win="http://v8.1c.ru/8.1/data/ui/colors/windows" xmlns:xs="http://www.w3.org/2001/XMLSchema" xmlns:xsi="http://www.w3.org/2001/XMLSchema-instance" version="2.10">
	<BackColor>style:FieldBackColor</BackColor>
	<GridEnabled>true</GridEnabled>
	<DrawGridMode>Lines</DrawGridMode>
	<GridHorizontalStep>20</GridHorizontalStep>
	<GridVerticalStep>20</GridVerticalStep>
	<PrintParameters>
		<TopMargin>10</TopMargin>
		<LeftMargin>10</LeftMargin>
		<BottomMargin>10</BottomMargin>
		<RightMargin>10</RightMargin>
		<BlackAndWhite>false</BlackAndWhite>
		<FitPageMode>Auto</FitPageMode>
	</PrintParameters>
	<Items>
		<Start id="1" uuid="abc53fc1-bf40-4306-8fec-b55bb0d2a44a">
			<Properties>
				<Name>Старт</Name>
				<Title>
					<v8:item>
						<v8:lang>ru</v8:lang>
						<v8:content>Старт</v8:content>
					</v8:item>
				</Title>
				<ToolTip/>
				<TabOrder>1</TabOrder>
				<BackColor>auto</BackColor>
				<TextColor>style:FormTextColor</TextColor>
				<LineColor>style:BorderColor</LineColor>
				<GroupNumber>0</GroupNumber>
				<ZOrder>0</ZOrder>
				<Hyperlink>false</Hyperlink>
				<Transparent>false</Transparent>
				<Font kind="AutoFont"/>
				<HorizontalAlign>Center</HorizontalAlign>
				<VerticalAlign>Center</VerticalAlign>
				<PictureLocation>Left</PictureLocation>
				<Location top="40" left="200" bottom="80" right="300"/>
				<Border width="1" gap="false">
					<v8ui:style xsi:type="sch:ConnectorLineType">Solid</v8ui:style>
				</Border>
				<Picture/>
				<PictureSize>AutoSize</PictureSize>
			</Properties>
			<Events>
				<Event name="BeforeStart"/>
			</Events>
		</Start>
		<ConnectionLine id="2">
			<Properties>
				<Name>Линия1</Name>
				<Title/>
				<ToolTip/>
				<TabOrder>2</TabOrder>
				<BackColor>auto</BackColor>
				<TextColor>style:FormTextColor</TextColor>
				<LineColor>style:BorderColor</LineColor>
				<GroupNumber>0</GroupNumber>
				<ZOrder>1</ZOrder>
				<Hyperlink>false</Hyperlink>
				<Transparent>false</Transparent>
				<Font kind="AutoFont"/>
				<HorizontalAlign>Center</HorizontalAlign>
				<VerticalAlign>Center</VerticalAlign>
				<PictureLocation>Left</PictureLocation>
				<PivotPoints>
					<Point x="250" y="80"/>
					<Point x="250" y="110"/>
					<Point x="260" y="110"/>
					<Point x="260" y="140"/>
				</PivotPoints>
				<Connect>
					<From>
						<Item>Старт</Item>
						<PortIndex>4</PortIndex>
					</From>
					<To>
						<Item>Выполнить</Item>
						<PortIndex>5</PortIndex>
					</To>
				</Connect>
				<Line width="1" gap="false">
					<v8ui:style xsi:type="sch:ConnectorLineType">Solid</v8ui:style>
				</Line>
				<DecorativeLine>false</DecorativeLine>
				<TextLocation>FirstSegment</TextLocation>
				<BeginArrow>None</BeginArrow>
				<EndArrow>Filled</EndArrow>
			</Properties>
		</ConnectionLine>
		<Completion id="3" uuid="62ceb989-b7ba-415c-917e-e9a4929235a0">
			<Properties>
				<Name>Завершение</Name>
				<Title>
					<v8:item>
						<v8:lang>ru</v8:lang>
						<v8:content>Завершение</v8:content>
					</v8:item>
				</Title>
				<ToolTip/>
				<TabOrder>3</TabOrder>
				<BackColor>auto</BackColor>
				<TextColor>style:FormTextColor</TextColor>
				<LineColor>style:BorderColor</LineColor>
				<GroupNumber>0</GroupNumber>
				<ZOrder>2</ZOrder>
				<Hyperlink>false</Hyperlink>
				<Transparent>false</Transparent>
				<Font kind="AutoFont"/>
				<HorizontalAlign>Center</HorizontalAlign>
				<VerticalAlign>Center</VerticalAlign>
				<PictureLocation>Left</PictureLocation>
				<Location top="480" left="200" bottom="540" right="300"/>
				<Border width="1" gap="false">
					<v8ui:style xsi:type="sch:ConnectorLineType">Solid</v8ui:style>
				</Border>
				<Picture/>
				<PictureSize>AutoSize</PictureSize>
			</Properties>
			<Events>
				<Event name="OnComplete"/>
			</Events>
		</Completion>
		<Activity id="4" uuid="105f8e25-5367-43e7-8c33-43ea35ae326c">
			<Properties>
				<Name>Выполнить</Name>
				<Title>
					<v8:item>
						<v8:lang>ru</v8:lang>
						<v8:content>Выполнить</v8:content>
					</v8:item>
				</Title>
				<ToolTip/>
				<TabOrder>4</TabOrder>
				<BackColor>auto</BackColor>
				<TextColor>style:FormTextColor</TextColor>
				<LineColor>style:BorderColor</LineColor>
				<GroupNumber>0</GroupNumber>
				<ZOrder>3</ZOrder>
				<Hyperlink>false</Hyperlink>
				<Transparent>false</Transparent>
				<Font kind="AutoFont"/>
				<HorizontalAlign>Center</HorizontalAlign>
				<VerticalAlign>Center</VerticalAlign>
				<PictureLocation>Left</PictureLocation>
				<Location top="140" left="200" bottom="200" right="320"/>
				<Border width="1" gap="false">
					<v8ui:style xsi:type="sch:ConnectorLineType">Solid</v8ui:style>
				</Border>
				<Picture/>
				<PictureSize>AutoSize</PictureSize>
				<TaskDescription>Выполнить</TaskDescription>
				<Explanation/>
				<Group>false</Group>
				<AddressingAttributes>
					<AddressingAttribute ref="Task.ЗадачаПользователя.AddressingAttribute.Пользователь">
						<Value xsi:nil="true"/>
					</AddressingAttribute>
				</AddressingAttributes>
			</Properties>
			<Events>
				<Event name="InteractiveActivationProcessing"/>
				<Event name="BeforeCreateTasks"/>
				<Event name="OnCreateTask">ВыполнитьПриСозданииЗадач</Event>
				<Event name="OnExecute">ВыполнитьПриВыполнении</Event>
				<Event name="CheckExecutionProcessing"/>
				<Event name="BeforeExecute"/>
				<Event name="BeforeExecuteInteractively"/>
			</Events>
		</Activity>
		<ConnectionLine id="5">
			<Properties>
				<Name>Линия2</Name>
				<Title/>
				<ToolTip/>
				<TabOrder>5</TabOrder>
				<BackColor>auto</BackColor>
				<TextColor>style:FormTextColor</TextColor>
				<LineColor>style:BorderColor</LineColor>
				<GroupNumber>0</GroupNumber>
				<ZOrder>4</ZOrder>
				<Hyperlink>false</Hyperlink>
				<Transparent>false</Transparent>
				<Font kind="AutoFont"/>
				<HorizontalAlign>Center</HorizontalAlign>
				<VerticalAlign>Center</VerticalAlign>
				<PictureLocation>Left</PictureLocation>
				<PivotPoints>
					<Point x="260" y="200"/>
					<Point x="260" y="230"/>
					<Point x="260" y="230"/>
					<Point x="260" y="260"/>
				</PivotPoints>
				<Connect>
					<From>
						<Item>Выполнить</Item>
						<PortIndex>4</PortIndex>
					</From>
					<To>
						<Item>Проверка</Item>
						<PortIndex>2</PortIndex>
					</To>
				</Connect>
				<Line width="1" gap="false">
					<v8ui:style xsi:type="sch:ConnectorLineType">Solid</v8ui:style>
				</Line>
				<DecorativeLine>false</DecorativeLine>
				<TextLocation>FirstSegment</TextLocation>
				<BeginArrow>None</BeginArrow>
				<EndArrow>Filled</EndArrow>
			</Properties>
		</ConnectionLine>
		<Condition id="6" uuid="166daef9-17a1-4c16-9c78-0efe509264fc">
			<Properties>
				<Name>ЗадачаВыполненаУспешно</Name>
				<Title>
					<v8:item>
						<v8:lang>ru</v8:lang>
						<v8:content>Задача выполнена успешно</v8:content>
					</v8:item>
				</Title>
				<ToolTip/>
				<TabOrder>6</TabOrder>
				<BackColor>auto</BackColor>
				<TextColor>style:FormTextColor</TextColor>
				<LineColor>style:BorderColor</LineColor>
				<GroupNumber>0</GroupNumber>
				<ZOrder>5</ZOrder>
				<Hyperlink>false</Hyperlink>
				<Transparent>false</Transparent>
				<Font kind="AutoFont"/>
				<HorizontalAlign>Center</HorizontalAlign>
				<VerticalAlign>Center</VerticalAlign>
				<PictureLocation>Left</PictureLocation>
				<Location top="360" left="200" bottom="420" right="300"/>
				<Border width="1" gap="false">
					<v8ui:style xsi:type="sch:ConnectorLineType">Solid</v8ui:style>
				</Border>
				<Picture/>
				<PictureSize>AutoSize</PictureSize>
				<TruePortIndex>3</TruePortIndex>
				<FalsePortIndex>1</FalsePortIndex>
			</Properties>
			<Events>
				<Event name="ConditionCheck">ЗадачаВыполненаУспешноПроверкаУсловия</Event>
			</Events>
		</Condition>
		<ConnectionLine id="7">
			<Properties>
				<Name>Линия3</Name>
				<Title>
					<v8:item>
						<v8:lang>ru</v8:lang>
						<v8:content>Нет</v8:content>
					</v8:item>
				</Title>
				<ToolTip/>
				<TabOrder>7</TabOrder>
				<BackColor>auto</BackColor>
				<TextColor>style:FormTextColor</TextColor>
				<LineColor>style:BorderColor</LineColor>
				<GroupNumber>0</GroupNumber>
				<ZOrder>6</ZOrder>
				<Hyperlink>false</Hyperlink>
				<Transparent>false</Transparent>
				<Font kind="AutoFont"/>
				<HorizontalAlign>Center</HorizontalAlign>
				<VerticalAlign>Center</VerticalAlign>
				<PictureLocation>Left</PictureLocation>
				<PivotPoints>
					<Point x="200" y="390"/>
					<Point x="180" y="390"/>
					<Point x="180" y="170"/>
					<Point x="200" y="170"/>
				</PivotPoints>
				<Connect>
					<From>
						<Item>ЗадачаВыполненаУспешно</Item>
						<PortIndex>1</PortIndex>
					</From>
					<To>
						<Item>Выполнить</Item>
						<PortIndex>1</PortIndex>
					</To>
				</Connect>
				<Line width="1" gap="false">
					<v8ui:style xsi:type="sch:ConnectorLineType">Solid</v8ui:style>
				</Line>
				<DecorativeLine>false</DecorativeLine>
				<TextLocation>FirstSegment</TextLocation>
				<BeginArrow>None</BeginArrow>
				<EndArrow>Filled</EndArrow>
			</Properties>
		</ConnectionLine>
		<ConnectionLine id="8">
			<Properties>
				<Name>Линия4</Name>
				<Title>
					<v8:item>
						<v8:lang>ru</v8:lang>
						<v8:content>Да</v8:content>
					</v8:item>
				</Title>
				<ToolTip/>
				<TabOrder>8</TabOrder>
				<BackColor>auto</BackColor>
				<TextColor>style:FormTextColor</TextColor>
				<LineColor>style:BorderColor</LineColor>
				<GroupNumber>0</GroupNumber>
				<ZOrder>7</ZOrder>
				<Hyperlink>false</Hyperlink>
				<Transparent>false</Transparent>
				<Font kind="AutoFont"/>
				<HorizontalAlign>Center</HorizontalAlign>
				<VerticalAlign>Center</VerticalAlign>
				<PictureLocation>Left</PictureLocation>
				<PivotPoints>
					<Point x="300" y="390"/>
					<Point x="320" y="390"/>
					<Point x="320" y="450"/>
					<Point x="250" y="450"/>
					<Point x="250" y="480"/>
				</PivotPoints>
				<Connect>
					<From>
						<Item>ЗадачаВыполненаУспешно</Item>
						<PortIndex>3</PortIndex>
					</From>
					<To>
						<Item>Завершение</Item>
						<PortIndex>2</PortIndex>
					</To>
				</Connect>
				<Line width="1" gap="false">
					<v8ui:style xsi:type="sch:ConnectorLineType">Solid</v8ui:style>
				</Line>
				<DecorativeLine>false</DecorativeLine>
				<TextLocation>FirstSegment</TextLocation>
				<BeginArrow>None</BeginArrow>
				<EndArrow>Filled</EndArrow>
			</Properties>
		</ConnectionLine>
		<Activity id="9" uuid="114bae88-29ff-4d5c-9e88-d7bbc6bca16f">
			<Properties>
				<Name>Проверка</Name>
				<Title>
					<v8:item>
						<v8:lang>ru</v8:lang>
						<v8:content>Проверка</v8:content>
					</v8:item>
				</Title>
				<ToolTip/>
				<TabOrder>9</TabOrder>
				<BackColor>auto</BackColor>
				<TextColor>style:FormTextColor</TextColor>
				<LineColor>style:BorderColor</LineColor>
				<GroupNumber>0</GroupNumber>
				<ZOrder>8</ZOrder>
				<Hyperlink>false</Hyperlink>
				<Transparent>false</Transparent>
				<Font kind="AutoFont"/>
				<HorizontalAlign>Center</HorizontalAlign>
				<VerticalAlign>Center</VerticalAlign>
				<PictureLocation>Left</PictureLocation>
				<Location top="260" left="200" bottom="300" right="320"/>
				<Border width="1" gap="false">
					<v8ui:style xsi:type="sch:ConnectorLineType">Solid</v8ui:style>
				</Border>
				<Picture/>
				<PictureSize>AutoSize</PictureSize>
				<TaskDescription>Проверка</TaskDescription>
				<Explanation/>
				<Group>false</Group>
				<AddressingAttributes>
					<AddressingAttribute ref="Task.ЗадачаПользователя.AddressingAttribute.Пользователь">
						<Value xsi:nil="true"/>
					</AddressingAttribute>
				</AddressingAttributes>
			</Properties>
			<Events>
				<Event name="InteractiveActivationProcessing"/>
				<Event name="BeforeCreateTasks"/>
				<Event name="OnCreateTask">ПроверкаПриСозданииЗадач</Event>
				<Event name="OnExecute"/>
				<Event name="CheckExecutionProcessing"/>
				<Event name="BeforeExecute"/>
				<Event name="BeforeExecuteInteractively"/>
			</Events>
		</Activity>
		<ConnectionLine id="10">
			<Properties>
				<Name>Линия5</Name>
				<Title/>
				<ToolTip/>
				<TabOrder>10</TabOrder>
				<BackColor>auto</BackColor>
				<TextColor>style:FormTextColor</TextColor>
				<LineColor>style:BorderColor</LineColor>
				<GroupNumber>0</GroupNumber>
				<ZOrder>9</ZOrder>
				<Hyperlink>false</Hyperlink>
				<Transparent>false</Transparent>
				<Font kind="AutoFont"/>
				<HorizontalAlign>Center</HorizontalAlign>
				<VerticalAlign>Center</VerticalAlign>
				<PictureLocation>Left</PictureLocation>
				<PivotPoints>
					<Point x="260" y="300"/>
					<Point x="260" y="330"/>
					<Point x="250" y="330"/>
					<Point x="250" y="360"/>
				</PivotPoints>
				<Connect>
					<From>
						<Item>Проверка</Item>
						<PortIndex>4</PortIndex>
					</From>
					<To>
						<Item>ЗадачаВыполненаУспешно</Item>
						<PortIndex>2</PortIndex>
					</To>
				</Connect>
				<Line width="1" gap="false">
					<v8ui:style xsi:type="sch:ConnectorLineType">Solid</v8ui:style>
				</Line>
				<DecorativeLine>false</DecorativeLine>
				<TextLocation>FirstSegment</TextLocation>
				<BeginArrow>None</BeginArrow>
				<EndArrow>Filled</EndArrow>
			</Properties>
		</ConnectionLine>
	</Items>
</GraphicalSchema>